vsec_tls/__init__.py
vsec_tls/__version__.py
vsec_tls/c_interface_wrapper.py
vsec_tls/exceptions.py
vsec_tls/profiles.py
vsec_tls/response.py
vsec_tls/session.py
vsec_tls/utils.py
vsec_tls/dependencies/ja3_utls.dll
vsec_tls/dependencies/libja3_utls.dylib
vsec_tls/dependencies/libja3_utls_amd64.so
vsec_tls/dependencies/libja3_utls_arm64.so
vsec_tls/dependencies/libvelum_secure.so
vsec_tls/dependencies/libvelum_secure_arm64.dylib
vsec_tls/dependencies/libvelum_secure_x86_64.dylib
vsec_tls/dependencies/velum_secure.dll
vsec_tls-0.7.1.dist-info/licenses/LICENSE
vsec_tls-0.7.1.dist-info/METADATA
vsec_tls-0.7.1.dist-info/WHEEL
vsec_tls-0.7.1.dist-info/top_level.txt
vsec_tls-0.7.1.dist-info/RECORD
